{"name": "J024403.83+004629.6", "Statistics": {}, "source": "--", "Gamma": "--", "L_X": "--", "NH": "--", "MBH": 987553.5014445221, "MBH_ESI": {}, "MBH_MagE": {}, "page.spect": {}, "SALT_spec": {}, "ESI2D": {}, "MagE2D": {}, "SALT2D": {}, "ra": 41.015959, "dec": 0.7748909, "rcsed": "https://dev-rcsed2.voxastro.org/catalog?q=cone(41.015959,0.7748909,0.011)", "page.html": NaN, "png with 2d": NaN, "png with fit": NaN, "Table from: ": "table_2K", "cutout": "https://www.legacysurvey.org/viewer/cutout.jpg?ra=41.015959&dec=0.7748909&layer=ls-dr9&pixscale=0.36&size=100"}