{"name": "J080527.31+091731.3", "Statistics": {}, "source": [], "Gamma": [], "L_X": [], "NH": [], "MBH": [141009.99887627029], "MBH_ESI": [], "MBH_MagE": [], "MBH_SALT": [], "ESIfull": [], "SALTfull": [], "MagEfull": [], "ESInonp": [], "SALTnonp": [], "MagEnonp": [], "page.html": [], "page_all_fit": [], "ra": 121.36379, "dec": 9.2920249, "rcsed": "https://dev-rcsed2.voxastro.org/catalog?q=cone(121.36379,9.2920249,0.011)", "Table from": "table_2K", "cutout": "https://www.legacysurvey.org/viewer/cutout.jpg?ra=121.36379&dec=9.2920249&layer=ls-dr9&pixscale=0.36&size=100"}