{"name": "J094919.08+000144.0", "Statistics": {}, "source": [], "Gamma": [], "L_X": [], "NH": [], "MBH": [423304.52671991807], "MBH_ESI": [], "MBH_MagE": [], "MBH_SALT": [], "ESIfull": [], "SALTfull": [], "MagEfull": [], "ESInonp": [], "SALTnonp": [], "MagEnonp": [], "page.html": [], "page_all_fit": [], "ra": 147.32951, "dec": 0.028902695, "rcsed": "https://dev-rcsed2.voxastro.org/catalog?q=cone(147.32951,0.028902695,0.011)", "Table from": "table_2K", "cutout": "https://www.legacysurvey.org/viewer/cutout.jpg?ra=147.32951&dec=0.028902695&layer=ls-dr9&pixscale=0.36&size=100"}