{"name": "J095256.61+211133.9", "Statistics": {}, "source": [], "Gamma": [], "L_X": [], "NH": [], "MBH": [642676.7686323137], "MBH_ESI": [], "MBH_MagE": [], "MBH_SALT": [], "ESIfull": [], "SALTfull": [], "MagEfull": [], "ESInonp": [], "SALTnonp": [], "MagEnonp": [], "page.html": [], "page_all_fit": [], "ra": 148.23587, "dec": 21.192748, "rcsed": "https://dev-rcsed2.voxastro.org/catalog?q=cone(148.23587,21.192748,0.011)", "Table from": "table_2K", "cutout": "https://www.legacysurvey.org/viewer/cutout.jpg?ra=148.23587&dec=21.192748&layer=ls-dr9&pixscale=0.36&size=100"}