{"name": "J104122.65+314650.5", "Statistics": {}, "source": [], "Gamma": [], "L_X": [], "NH": [], "MBH": [107900.25681599893], "MBH_ESI": [], "MBH_MagE": [], "MBH_SALT": [], "ESIfull": [], "SALTfull": [], "MagEfull": [], "ESInonp": [], "SALTnonp": [], "MagEnonp": [], "page.html": [], "page_all_fit": [], "ra": 160.34439, "dec": 31.78069, "rcsed": "https://dev-rcsed2.voxastro.org/catalog?q=cone(160.34439,31.78069,0.011)", "Table from": "table_2K", "cutout": "https://www.legacysurvey.org/viewer/cutout.jpg?ra=160.34439&dec=31.78069&layer=ls-dr9&pixscale=0.36&size=100"}