{"name": "J105605.58+005903.6", "Statistics": {}, "source": "--", "Gamma": "--", "L_X": "--", "NH": "--", "MBH": 279885.4746271657, "MBH_ESI": {}, "MBH_MagE": {}, "page.spect": {}, "SALT_spec": {}, "ESI2D": {}, "MagE2D": {}, "SALT2D": {}, "ra": 164.02327, "dec": 0.98433886, "rcsed": "https://dev-rcsed2.voxastro.org/catalog?q=cone(164.02327,0.98433886,0.011)", "page.html": NaN, "png with 2d": NaN, "png with fit": NaN, "Table from: ": "table_2K", "cutout": "https://www.legacysurvey.org/viewer/cutout.jpg?ra=164.02327&dec=0.98433886&layer=ls-dr9&pixscale=0.36&size=100"}