{"name": "J123332.44+105945.4", "Statistics": {}, "source": [], "Gamma": [], "L_X": [], "NH": [], "MBH": [342458.4414321946], "MBH_ESI": [], "MBH_MagE": [], "MBH_SALT": [], "ESIfull": [], "SALTfull": [], "MagEfull": [], "ESInonp": [], "SALTnonp": [], "MagEnonp": [], "page.html": [], "page_all_fit": [], "ra": 188.38516, "dec": 10.995934, "rcsed": "https://dev-rcsed2.voxastro.org/catalog?q=cone(188.38516,10.995934,0.011)", "Table from": "table_2K", "cutout": "https://www.legacysurvey.org/viewer/cutout.jpg?ra=188.38516&dec=10.995934&layer=ls-dr9&pixscale=0.36&size=100"}