{"name": "J165409.12+244704.5", "Statistics": {}, "source": [], "Gamma": [], "L_X": [], "NH": [], "MBH": [623249.9355279235], "MBH_ESI": [], "MBH_MagE": [], "MBH_SALT": [], "ESIfull": [], "SALTfull": [], "MagEfull": [], "ESInonp": [], "SALTnonp": [], "MagEnonp": [], "page.html": [], "page_all_fit": [], "ra": 253.53798, "dec": 24.784596, "rcsed": "https://dev-rcsed2.voxastro.org/catalog?q=cone(253.53798,24.784596,0.011)", "Table from": "table_2K", "cutout": "https://www.legacysurvey.org/viewer/cutout.jpg?ra=253.53798&dec=24.784596&layer=ls-dr9&pixscale=0.36&size=100"}