{"name": "J215330.75+010002.9", "Statistics": {}, "source": [], "Gamma": [], "L_X": [], "NH": [], "MBH": [726906.0815223972], "MBH_ESI": [], "MBH_MagE": [], "MBH_SALT": [], "ESIfull": [], "SALTfull": [], "MagEfull": [], "ESInonp": [], "SALTnonp": [], "MagEnonp": [], "page.html": [], "page_all_fit": [], "ra": 328.37813, "dec": 1.0008106, "rcsed": "https://dev-rcsed2.voxastro.org/catalog?q=cone(328.37813,1.0008106,0.011)", "Table from": "table_2K", "cutout": "https://www.legacysurvey.org/viewer/cutout.jpg?ra=328.37813&dec=1.0008106&layer=ls-dr9&pixscale=0.36&size=100"}