{"name": "J142257.73+225441.4", "Statistics": {}, "source": "--", "Gamma": "--", "L_X": "--", "NH": "--", "MBH": 45988.92742308911, "MBH_ESI": {}, "MBH_MagE": {}, "page.spect": {}, "SALT_spec": {}, "ESI2D": {}, "MagE2D": {}, "SALT2D": {}, "ra": 215.74053, "dec": 22.911507, "rcsed": "https://dev-rcsed2.voxastro.org/catalog?q=cone(215.74053,22.911507,0.011)", "page.html": NaN, "png with 2d": NaN, "png with fit": NaN, "Table from: ": "table_2K", "cutout": "https://www.legacysurvey.org/viewer/cutout.jpg?ra=215.74053&dec=22.911507&layer=ls-dr9&pixscale=0.36&size=100"}