{"name": "J163007.28+405248.5", "Statistics": {"0": {}, "1": {}}, "source": {"0": "xmm archive", "1": "--"}, "Gamma": {"0": "--", "1": "--"}, "L_X": {"0": 1.273260709112238e+40, "1": "--"}, "NH": {"0": "--", "1": "--"}, "MBH": {"0": 659208.9659318707, "1": 465998.2165199959}, "MBH_ESI": {}, "MBH_MagE": {}, "page.spect": {}, "SALT_spec": {}, "ESI2D": {}, "MagE2D": {}, "SALT2D": {}, "ra": 247.53035, "dec": 40.880149, "rcsed": "https://dev-rcsed2.voxastro.org/catalog?q=cone(247.53035,40.880149,0.011)", "page.html": "http://gal-03.sai.msu.ru/~vtoptun/lowmass/J163007.28+405248.5/page.html", "png with 2d": NaN, "png with fit": NaN, "Table from: ": "table_2K"}